DRKApp/__init__.py
DRKApp-0.2.0.dist-info/METADATA
DRKApp-0.2.0.dist-info/WHEEL
DRKApp-0.2.0.dist-info/top_level.txt
DRKApp-0.2.0.dist-info/RECORD
