Metadata-Version: 2.1
Name: DRKApp
Version: 0.2.0
Summary: A Python package to access the DRK APP API
Home-page: https://github.com/iamrraj/Mattr_lib
Author: Rahul Raj
Author-email: rajr97333@gmail.com
License: MIT
Keywords: DRK APP API
Platform: UNKNOWN
Classifier: Development Status :: 3 - Alpha
Classifier: Intended Audience :: Developers
Classifier: License :: OSI Approved :: MIT License
Classifier: Programming Language :: Python :: 3
Classifier: Programming Language :: Python :: 3.6
Classifier: Programming Language :: Python :: 3.7
Classifier: Programming Language :: Python :: 3.8
Requires-Dist: requests
